endi_base/__init__.py
endi_base/consts.py
endi_base/exception.py
endi_base/mail.py
endi_base/models/__init__.py
endi_base/models/base.py
endi_base/models/initialize.py
endi_base/models/mixins.py
endi_base/models/types.py
endi_base/models/utils.py
endi_base/utils/__init__.py
endi_base/utils/ascii.py
endi_base/utils/date.py
endi_base/utils/export.py
endi_base/utils/math.py
endi_base/utils/renderers.py
endi_base/utils/strings.py
endi_base-6.7.1.dist-info/LICENSE.txt
endi_base-6.7.1.dist-info/METADATA
endi_base-6.7.1.dist-info/WHEEL
endi_base-6.7.1.dist-info/entry_points.txt
endi_base-6.7.1.dist-info/top_level.txt
endi_base-6.7.1.dist-info/RECORD
